clickhouse_driver_http/__init__.py
clickhouse_driver_http-0.1.6.dist-info/METADATA
clickhouse_driver_http-0.1.6.dist-info/WHEEL
clickhouse_driver_http-0.1.6.dist-info/top_level.txt
clickhouse_driver_http-0.1.6.dist-info/RECORD
