Metadata-Version: 2.1
Name: clickhouse-driver-http
Version: 0.1.6
Summary: Lightweight HTTP client for ClickHouse
Home-page: UNKNOWN
Author: Nikita Krachkovskiy
Author-email: sudokns@gmail.com
License: UNKNOWN
Keywords: clickhouse,http,driver,database
Platform: UNKNOWN
Classifier: Programming Language :: Python :: 3
Classifier: License :: OSI Approved :: MIT License
Classifier: Operating System :: OS Independent
Requires-Python: >=3.7
Requires-Dist: requests (>=2.25.1)
Requires-Dist: pandas (>=1.3.0) ; extra == "pandas"
Provides-Extra: pandas
Requires-Dist: pandas (>=1.3.0) ; extra == 'pandas'
